fibos-2.3.1.dist-info/RECORD
fibos-2.3.1.dist-info/WHEEL
fibos-2.3.1.dist-info/METADATA
fibos/read_prot.py
fibos/respak.py
fibos/occsurf75.dylib
fibos/radii
fibos/main75.dylib
fibos/renum75.dylib
fibos/ds75.dylib
fibos/__init__.py
fibos/surfcal76.dylib
fibos/cleaner.py
fibos/utils.py
fibos/main_intermediary.py
fibos/manage_os.py
fibos/read_Disp.py
fibos/set_parameters.py
fibos/respak75.dylib
fibos/folders_manipulate.py
fibos/pattern
fibos/read_os.py
fibos/.dylibs/libgfortran.5.dylib
fibos/.dylibs/libquadmath.0.dylib
fibos/.dylibs/libgcc_s.1.1.dylib
fibos/fortran/params.h
fibos/fortran/assign_qr.h
fibos/fortran/input_sims.h
fibos/fortran/surf-sims.h
