Metadata-Version: 2.1
Name: fibos
Version: 2.3.1
Summary: Package to calculate Occluded Surfaces
Author: Herson Hebert Mendes Soares
Requires-Python: >=3.9
Requires-Dist: numpy>=1.22.4
Requires-Dist: biopython>=1.84
Requires-Dist: testresources>=2.0.1
Requires-Dist: pandas>=2.2.3
